Workbook

Sheet Assumptions
C1: Team Travi -Assumptions
C4: Commission model only
C5: Booking Commission | D5: 15-25% per booking
C6: Earnings Travi | D6: 5-7% per booking
C8: Users
C9: Active monthly users in the beginning | D9: 2000
C10: Average booking value per user | D10: =D39 -> 370
C11: Booking Conversion Rate | D11: 0.15
C13: Marketing
C14: Channel 1 | D14: Landing Page/Newsletter
C15: Channel 2 | D15: Influencer
C16: Channel 3 | D16: Web-Ads
C19: Overhead & Tools
C20: Number of founders | D20: 4
C21: Tools | D21: Office 365, Pycharm,etc.
C24: Average booking value per user (Flight + Hotel)
C25: Avergage Flight Booking Cost
C26: Intra-Europe (Gen Z travel) | D26: 80-150€
C27: International (e.g. Europe–Asia) | D27: 400-900€
C28: Average Hotel/Accommodation Booking
C29: Hostel (2 nights) | D29: 60-100€
C30: Hotel (2–3 nights) | D30: 150-250€
C31: Airbnb (split) | D31: €100–€150
C32: Tours, Tickets & Local Experiences
C33: City tours, museum, nightlife passes | D33: 20-50€
C34: Adventure (e.g. diving, hot air balloon) | D34: 80–150€
C35: Total Booking Value Per User (+-10% stdv.)
C36: Flights | D36: 150
C37: Accommodation | D37: 180
C38: Activities/Tours | D38: 40
C39: Total Booking Value Per User (+-10% stdv.) | D39: =SUM(D36:D38) -> 370
C40: Lower End (-10%) | D40: =D39*0.9 -> 333
C41: Upper End (+10%) | D41: =D39*1.1 -> 407

Sheet P&L
C1: Team Travi - P&L
D3: 45658 | E3: 45689 | F3: 45717 | G3: 45748 | H3: 45778 | I3: 45809 | J3: 45839 | K3: 45870 | L3: 45901 | M3: 45931 | N3: 45962 | O3: 45992 | P3: 46023 | Q3: 46054 | R3: 46082 | S3: 46113 | T3: 46143 | U3: 46174 | V3: 46204 | W3: 46235 | X3: 46266 | Y3: 46296 | Z3: 46327 | AA3: 46357 | AB3: 46388 | AC3: 46419 | AD3: 46447 | AE3: 46478 | AF3: 46508 | AG3: 46539 | AH3: 46569 | AI3: 46600 | AJ3: 46631 | AK3: 46661 | AL3: 46692 | AM3: 46722
C4: Profit & Loss
C5: Comission | D5: 0.05 | E5: 0.05 | F5: 0.05 | G5: 0.05 | H5: 0.05 | I5: 0.05 | J5: 0.05 | K5: 0.05 | L5: 0.05 | M5: 0.05 | N5: 0.05 | O5: 0.05 | P5: 0.05 | Q5: 0.05 | R5: 0.05 | S5: 0.05 | T5: 0.05 | U5: 0.05 | V5: 0.05 | W5: 0.05 | X5: 0.05 | Y5: 0.05 | Z5: 0.05 | AA5: 0.05 | AB5: 0.05 | AC5: 0.05 | AD5: 0.05 | AE5: 0.05 | AF5: 0.05 | AG5: 0.05 | AH5: 0.05 | AI5: 0.05 | AJ5: 0.05 | AK5: 0.05 | AL5: 0.05 | AM5: 0.05
C7: Monthly active users | D7: =Assumptions!$D$9 -> 2000 | E7: =Assumptions!$D$9 -> 2000 | F7: =Assumptions!$D$9 -> 2000 | G7: 2750 | H7: 2750 | I7: 2750 | J7: 2750 | K7: 2750 | L7: 2750 | M7: 3500 | N7: 3500 | O7: 3500 | P7: 3500 | Q7: 3500 | R7: 4200 | S7: 4200 | T7: 4200 | U7: 5000 | V7: 5000 | W7: 5000 | X7: 5000 | Y7: 5000 | Z7: 5000 | AA7: 5000 | AB7: 5000 | AC7: =Assumptions!$D$9 -> 2000 | AD7: 5000 | AE7: =Assumptions!$D$9 -> 2000 | AF7: 5000 | AG7: =Assumptions!$D$9 -> 2000 | AH7: =Assumptions!$D$9 -> 2000 | AI7: 5000 | AJ7: 5000 | AK7: 5000 | AL7: 5000 | AM7: 5000
C9: Booking Conversion Rate | D9: =Assumptions!$D$11 -> 0.15 | E9: =Assumptions!$D$11 -> 0.15 | F9: 0.2 | G9: =Assumptions!$D$11 -> 0.15 | H9: 0.2 | I9: =Assumptions!$D$11 -> 0.15 | J9: =Assumptions!$D$11 -> 0.15 | K9: =Assumptions!$D$11 -> 0.15 | L9: =Assumptions!$D$11 -> 0.15 | M9: =Assumptions!$D$11 -> 0.15 | N9: 0.2 | O9: =Assumptions!$D$11 -> 0.15 | P9: =Assumptions!$D$11 -> 0.15 | Q9: =Assumptions!$D$11 -> 0.15 | R9: =Assumptions!$D$11 -> 0.15 | S9: =Assumptions!$D$11 -> 0.15 | T9: 0.2 | U9: =Assumptions!$D$11 -> 0.15 | V9: =Assumptions!$D$11 -> 0.15 | W9: =Assumptions!$D$11 -> 0.15 | X9: 0.2 | Y9: 0.35 | Z9: =Assumptions!$D$11 -> 0.15 | AA9: =Assumptions!$D$11 -> 0.15 | AB9: =Assumptions!$D$11 -> 0.15 | AC9: 0.2 | AD9: =Assumptions!$D$11 -> 0.15 | AE9: =Assumptions!$D$11 -> 0.15 | AF9: =Assumptions!$D$11 -> 0.15 | AG9: 0.2 | AH9: =Assumptions!$D$11 -> 0.15 | AI9: =Assumptions!$D$11 -> 0.15 | AJ9: =Assumptions!$D$11 -> 0.15 | AK9: =Assumptions!$D$11 -> 0.15 | AL9: 0.2 | AM9: =Assumptions!$D$11 -> 0.15
C11: Average booking value per user (Flight + Hotel per user) | D11: =Assumptions!$D$10 -> 370 | E11: =Assumptions!$D$10 -> 370 | F11: =Assumptions!$D$10 -> 370 | G11: =Assumptions!$D$10 -> 370 | H11: =Assumptions!$D$10 -> 370 | I11: =Assumptions!$D$10 -> 370 | J11: =Assumptions!$D$10 -> 370 | K11: =Assumptions!$D$10 -> 370 | ... AM11: =Assumptions!$D$10 -> 370
C13: # of Bookings | D13: =D7*D9 -> 300 | E13: =E7*E9 -> 300 | F13: =F7*F9 -> 400 | G13: =G7*G9 -> 412.5 | H13: =H7*H9 -> 550 | I13: =I7*I9 -> 412.5 | J13: =J7*J9 -> 412.5 | K13: =K7*K9 -> 412.5 | ... AM13: =AM7*AM9 -> 750
C15: Revenue (Bookings) | D15: =(D13*D11)*D5 -> 5550 | E15: =(E13*E11)*E5 -> 5550 | F15: =(F13*F11)*F5 -> 7400 | G15: =(G13*G11)*G5 -> 7631.25 | H15: =(H13*H11)*H5 -> 10175 | I15: =(I13*I11)*I5 -> 7631.25 | J15: =(J13*J11)*J5 -> 7631.25 | K15: =(K13*K11)*K5 -> 7631.25 | ... AM15: =(AM13*AM11)*AM5 -> 13875
C17: Discounts | D17: 0 | E17: 0 | F17: 0 | G17: 0 | H17: 0 | I17: 0 | J17: 0 | K17: 0 | L17: 0 | M17: 0 | N17: 0 | O17: 0 | P17: 0 | Q17: 0 | R17: 0 | S17: 0 | T17: 0 | U17: 0 | V17: 0 | W17: 0 | X17: 0 | Y17: 0 | Z17: 0 | AA17: 0 | AB17: 0 | AC17: 0 | AD17: 0 | AE17: 0 | AF17: 0 | AG17: 0 | AH17: 0 | AI17: 0 | AJ17: 0 | AK17: 0 | AL17: 0 | AM17: 0
C19: Sales & Marketing Cost | D19: =D20+D21 -> 2800 | E19: =E20+E21 -> 2800 | F19: =F20+F21 -> 2300 | G19: =G20+G21 -> 2300 | H19: =H20+H21 -> 2300 | I19: =I20+I21 -> 2300 | J19: =J20+J21 -> 2300 | K19: =K20+K21 -> 2300 | ... AM19: =AM20+AM21 -> 1800
C20: Marketing | D20: 2000 | E20: 2000 | F20: 1500 | G20: 1500 | H20: 1500 | I20: 1500 | J20: 1500 | K20: 1500 | L20: 1000 | M20: 1000 | N20: 1000 | O20: 1000 | P20: 1000 | Q20: 1000 | R20: 1000 | S20: 1000 | T20: 1000 | U20: 1000 | V20: 1000 | W20: 1000 | X20: 1000 | Y20: 1000 | Z20: 1000 | AA20: 1000 | AB20: 1000 | AC20: 1000 | AD20: 1000 | AE20: 1000 | AF20: 1000 | AG20: 1000 | AH20: 1000 | AI20: 1000 | AJ20: 1000 | AK20: 1000 | AL20: 1000 | AM20: 1000
C21: Sales | D21: 800 | E21: 800 | F21: 800 | G21: 800 | H21: 800 | I21: 800 | J21: 800 | K21: 800 | L21: 800 | M21: 800 | N21: 800 | O21: 800 | P21: 800 | Q21: 800 | R21: 800 | S21: 800 | T21: 800 | U21: 800 | V21: 800 | W21: 800 | X21: 800 | Y21: 800 | Z21: 800 | AA21: 800 | AB21: 800 | AC21: 800 | AD21: 800 | AE21: 800 | AF21: 800 | AG21: 800 | AH21: 800 | AI21: 800 | AJ21: 800 | AK21: 800 | AL21: 800 | AM21: 800
C23: Production | D23: 20 | E23: 20 | F23: 20 | G23: 20 | H23: 20 | I23: 20 | J23: 20 | K23: 20 | L23: 20 | M23: 20 | N23: 20 | O23: 20 | P23: 20 | Q23: 20 | R23: 20 | S23: 20 | T23: 20 | U23: 20 | V23: 20 | W23: 20 | X23: 20 | Y23: 20 | Z23: 20 | AA23: 20 | AB23: 20 | AC23: 20 | AD23: 20 | AE23: 20 | AF23: 20 | AG23: 20 | AH23: 20 | AI23: 20 | AJ23: 20 | AK23: 20 | AL23: 20 | AM23: 20
C26: Overhead | D26: =D27+D28 -> 2100 | E26: =E27+E28 -> 2100 | F26: =F27+F28 -> 2100 | G26: =G27+G28 -> 2100 | H26: =H27+H28 -> 2100 | I26: =I27+I28 -> 2100 | J26: =J27+J28 -> 2100 | K26: =K27+K28 -> 2100 | ... AM26: =AM27+AM28 -> 2300
C27: HR | D27: 1800 | E27: 1800 | F27: 1800 | G27: 1800 | H27: 1800 | I27: 1800 | J27: 1800 | K27: 1800 | L27: 1800 | M27: 1800 | N27: 1800 | O27: 1800 | P27: 1800 | Q27: 1800 | R27: 1800 | S27: 1800 | T27: 1800 | U27: 1800 | V27: 1800 | W27: 1800 | X27: 1800 | Y27: 1800 | Z27: 1800 | AA27: 1800 | AB27: 1800 | AC27: 1800 | AD27: 1800 | AE27: 1800 | AF27: 1800 | AG27: 1800 | AH27: 1800 | AI27: 2000 | AJ27: 2000 | AK27: 2000 | AL27: 2000 | AM27: 2000
C28: General Cost | D28: 300 | E28: 300 | F28: 300 | G28: 300 | H28: 300 | I28: 300 | J28: 300 | K28: 300 | L28: 300 | M28: 300 | N28: 300 | O28: 300 | P28: 300 | Q28: 300 | R28: 300 | S28: 300 | T28: 300 | U28: 300 | V28: 300 | W28: 300 | X28: 300 | Y28: 300 | Z28: 300 | AA28: 300 | AB28: 300 | AC28: 300 | AD28: 300 | AE28: 300 | AF28: 300 | AG28: 300 | AH28: 300 | AI28: 300 | AJ28: 300 | AK28: 300 | AL28: 300 | AM28: 300
C30: EBITDA | D30: =D15-D17-D19-D23-D26 -> 630 | E30: =E15-E17-E19-E23-E26 -> 630 | F30: =F15-F17-F19-F23-F26 -> 2980 | G30: =G15-G17-G19-G23-G26 -> 3211.25 | H30: =H15-H17-H19-H23-H26 -> 5755 | I30: =I15-I17-I19-I23-I26 -> 3211.25 | J30: =J15-J17-J19-J23-J26 -> 3211.25 | K30: =K15-K17-K19-K23-K26 -> 3211.25 | ... AM30: =AM15-AM17-AM19-AM23-AM26 -> 9755

Sheet Break Even Calculation
C1: Team Travi - Break-Even Calculation
C5: Commission Rate (Travi) | D5: 0.05
C6: Booking Value/User | D6: 370
C7: Revenue/Booking | D7: =D5*D6 -> 18.5
C8: Fixed Costs | D8: ='P&L'!D23+'P&L'!D21+'P&L'!D27+'P&L'!D28 -> 2920
C10: Break-Even Calculation (bookings/month) | D10: =ROUNDUP(D8/D7,0.75) -> 158
C13: Bookings | D13: Revenue (€) | E13: Fixed Cost (€) | F13: Profit (EBITDA)
C14: 0 | D14: 0 | E14: =$D$8 -> 2920 | F14: =D14-E14 -> -2920
C15: 50 | D15: =C15*$D$6*$D$5 -> 925 | E15: =$D$8 -> 2920 | F15: =D15-E15 -> -1995
C16: 100 | D16: =C16*$D$6*$D$5 -> 1850 | E16: =$D$8 -> 2920 | F16: =D16-E16 -> -1070
C17: 150 | D17: =C17*$D$6*$D$5 -> 2775 | E17: =$D$8 -> 2920 | F17: =D17-E17 -> -145
C18: 158 | D18: =C18*$D$6*$D$5 -> 2923 | E18: =$D$8 -> 2920 | F18: =D18-E18 -> 3
C19: 200 | D19: =C19*$D$6*$D$5 -> 3700 | E19: =$D$8 -> 2920 | F19: =D19-E19 -> 780
C20: 300 | D20: =C20*$D$6*$D$5 -> 5550 | E20: =$D$8 -> 2920 | F20: =D20-E20 -> 2630
C25: Break-Even Calculation (bookings/month)

Sheet Customer Aquisition Costs
C1: Team Travi - Customer Aquisition Costs (CAC)
D5: 45658 | E5: 45689 | F5: 45717 | G5: 45748 | H5: 45778 | I5: 45809 | J5: 45839 | K5: 45870 | L5: 45901 | M5: 45931 | N5: 45962 | O5: 45992 | P5: 46023 | Q5: 46054 | R5: 46082 | S5: 46113 | T5: 46143 | U5: 46174 | V5: 46204 | W5: 46235 | X5: 46266 | Y5: 46296 | Z5: 46327 | AA5: 46357 | AB5: 46388 | AC5: 46419 | AD5: 46447 | AE5: 46478 | AF5: 46508 | AG5: 46539 | AH5: 46569 | AI5: 46600 | AJ5: 46631 | AK5: 46661 | AL5: 46692 | AM5: 46722
C6: CAC Calculation
C7: Total CAC Spend | D7: ='P&L'!D20 -> 2000 | E7: ='P&L'!E20 -> 2000 | F7: ='P&L'!F20 -> 1500 | G7: ='P&L'!G20 -> 1500 | H7: ='P&L'!H20 -> 1500 | I7: ='P&L'!I20 -> 1500 | J7: ='P&L'!J20 -> 1500 | K7: ='P&L'!K20 -> 1500 | ... AM7: ='P&L'!AM20 -> 1000
C9: Number of New Customers | D9: ='P&L'!D7*'P&L'!D9 -> 300 | E9: ='P&L'!E7*'P&L'!E9 -> 300 | F9: ='P&L'!F7*'P&L'!F9 -> 400 | G9: ='P&L'!G7*'P&L'!G9 -> 412.5 | H9: ='P&L'!H7*'P&L'!H9 -> 550 | I9: ='P&L'!I7*'P&L'!I9 -> 412.5 | J9: ='P&L'!J7*'P&L'!J9 -> 412.5 | K9: ='P&L'!K7*'P&L'!K9 -> 412.5 | ... AM9: ='P&L'!AM7*'P&L'!AM9 -> 750
C11: CAC (per booking customer) | D11: =D7/D9 -> 6.6666667 | E11: =E7/E9 -> 6.6666667 | F11: =F7/F9 -> 3.75 | G11: =G7/G9 -> 3.6363636 | H11: =H7/H9 -> 2.7272727 | I11: =I7/I9 -> 3.6363636 | J11: =J7/J9 -> 3.6363636 | K11: =K7/K9 -> 3.6363636 | ... AM11: =AM7/AM9 -> 1.3333333
C16: Customer Aquisition Costs (CAC) per booking customer

Sheet Market Size
C1: Market Size - Understanding the Market
C3: TAM (Total Addressable Market) | H3: Sources
C5: 2.5 | D5: Billion Gen Z worldwide | H5: https://cropink.com/generation-z-marketing-statistics
C6: 0.6 | D6: Gen - Z which are travelling (25%) | H6: https://www.peekpro.com/blog/gen-z-travel-trends
C7: 800 | D7: € Travel expenses (annually) 2-3x 400€ trips | H7: https://explodingtopics.com/blog/gen-z-stats?utm_source=chatgpt.com#top-2025-generation-z-statistics
H8: https://www.gfk.com/hubfs/Global%20Gen%20Z%20and%20Millennails_New%20Preview%20Report-1.pdf?utm
C9: TAM | D9: =C6*C7 -> 480 | E9: Billion (yearly) | H9: https://media.market.us/gen-z-statistics/?utm
C13: SAM (Serviceable Addressable Market)
C15: Target group → Gen Z in US & Europe, smartphone-savvy, willing to travel in groups (25%)
C16: 0.15 | D16: Million Gen Z in US & Europe
C17: =C16*0.25 -> 0.0375 | D17: Gen - Z which are travelling (25%)
C18: 800 | D18: € Travel expenses (annually) 2-3x 400€ trips
C20: SAM | D20: =C17*C18 -> 30 | E20: Billion (yearly)
C23: SOM (Service Obtainable Market)
C25: Target group → Users in Western Europe who can be reached at short notice
C27: 135600 | D27: Estimate of our users (until 2027)
C28: 800 | D28: € average booking value per year/user
C29: 0.05 | D29: Travi commission
C31: SOM | D31: =C27*C28*C29 -> 5424000 | E31: (yearly)
E32: own assumptions

Sheet Cashflow
A1: Cashflow

Sheet Bilanz
A1: Bilanz
F2: 2023 | G2: 2024 | H2: 2025 | I2: 2026 | J2: 2027
A3: Aktiva
C4: Anlagevermögen | E4: 000€
B5: Umlaufvermögen
C6: Barmittel (Kassenbestand) | E6: 000€
C7: Geldanlage | E7: 000€
C8: Forderungen aus Lieferungen und Leistungen | E8: 000€
C9: Lagerbestand (Vorräte) | E9: 000€
B10: Summe Umlaufvermögen | E10: 000€
A11: Summe Aktiva | E11: 000€
A13: Passiva
B14: Eigenkapital
C15: gezeichnetes Kapital | E15: 000€
C16: Eigenkapital (ohne gez. Kapital) | E16: 000€
C17: Gewinnrücklage inkl. Gewinn- / Verlustvorträge | E17: 000€
B18: Summe Eigenkapital | E18: 000€
B20: Verbindlichkeiten
C21: Verbindlichkeiten aus Lieferungen und Leistungen | E21: 000€
C22: Verbindlichkeiten gegenüber Kreditinstituten | E22: 000€
B23: Summe Verbindlichkeiten | E23: 000€
A24: Summe Passiva | E24: 000€
